uuid_mcp/__init__.py
uuid_mcp/server.py
uuid_mcp-0.1.0.dist-info/METADATA
uuid_mcp-0.1.0.dist-info/WHEEL
uuid_mcp-0.1.0.dist-info/entry_points.txt
uuid_mcp-0.1.0.dist-info/top_level.txt
uuid_mcp-0.1.0.dist-info/RECORD
