Metadata-Version: 2.4
Name: uuid-mcp
Version: 0.1.0
Summary: A simple MCP server that provides a tool to generate UUIDs
Keywords: mcp,uuid,model-context-protocol,cursor
Classifier: Development Status :: 4 - Beta
Classifier: Intended Audience :: Developers
Classifier: Programming Language :: Python :: 3
Classifier: Programming Language :: Python :: 3.8
Classifier: Programming Language :: Python :: 3.9
Classifier: Programming Language :: Python :: 3.10
Classifier: Programming Language :: Python :: 3.11
Classifier: Programming Language :: Python :: 3.12
Requires-Python: >=3.8
Requires-Dist: mcp>=0.9.0
